<?xml version='1.0' encoding='UTF-8'?><factura version='1.1.0' id='comprobante'><infoTributaria><ambiente>2</ambiente><tipoEmision>1</tipoEmision><razonSocial>GUATO CAIZA GEOCONDA MARGOTH</razonSocial><nombreComercial>MAX CHICKEN</nombreComercial><ruc>1803686300001</ruc><claveAcceso>1501202301180368630000120010010000006061234567811</claveAcceso><codDoc>01</codDoc><estab>001</estab><ptoEmi>001</ptoEmi><secuencial>000000606</secuencial><dirMatriz>COMERCIAL  10 DE AGOSTO S/N Y FRANCISCO MOSCOSO</dirMatriz></infoTributaria><infoFactura><fechaEmision>15/01/2023</fechaEmision><dirEstablecimiento>10 DE AGOSTO S/N Y FRANCISCO MOSCOSO</dirEstablecimiento><obligadoContabilidad>NO</obligadoContabilidad><tipoIdentificacionComprador>05</tipoIdentificacionComprador><razonSocialComprador>PESANTEZ SAMANIEGO CLARA FRANCISCA</razonSocialComprador><identificacionComprador>0101149565</identificacionComprador><totalSinImpuestos>31</totalSinImpuestos><totalDescuento>0</totalDescuento><totalConImpuestos><totalImpuesto><codigo>2</codigo><codigoPorcentaje>0</codigoPorcentaje><baseImponible>31</baseImponible><valor>0.00</valor></totalImpuesto></totalConImpuestos><propina>0.00</propina><importeTotal>31</importeTotal><moneda>DOLAR</moneda><pagos><pago><formaPago>01</formaPago><total>31</total></pago></pagos></infoFactura><detalles><detalle><codigoPrincipal>01</codigoPrincipal><codigoAuxiliar>01</codigoAuxiliar><descripcion>ALIMENTACION</descripcion><cantidad>1</cantidad><precioUnitario>31</precioUnitario><descuento>0</descuento><precioTotalSinImpuesto>31</precioTotalSinImpuesto><impuestos><impuesto><codigo>2</codigo><codigoPorcentaje>0</codigoPorcentaje><tarifa>0</tarifa><baseImponible>31</baseImponible><valor>0</valor></impuesto></impuestos></detalle></detalles><infoAdicional><campoAdicional nombre='Direccion'>ADOLOFO TORRES 2-55</campoAdicional><campoAdicional nombre='Telefono'>0995960491</campoAdicional><campoAdicional nombre='Email'>paquiitapesantezo@gmail.com</campoAdicional><campoAdicional nombre='Observaciones'> CONTRIBUYENTE REGIMEN RIMPE             </campoAdicional></infoAdicional></factura>