<?xml version='1.0' encoding='UTF-8'?><factura version='1.1.0' id='comprobante'><infoTributaria><ambiente>2</ambiente><tipoEmision>1</tipoEmision><razonSocial>GUATO CAIZA GEOCONDA MARGOTH</razonSocial><nombreComercial>MAX CHICKEN</nombreComercial><ruc>1803686300001</ruc><claveAcceso>2505202301180368630000120011000000002661234567811</claveAcceso><codDoc>01</codDoc><estab>001</estab><ptoEmi>100</ptoEmi><secuencial>000000266</secuencial><dirMatriz>COMERCIAL  10 DE AGOSTO S/N Y FRANCISCO MOSCOSO</dirMatriz></infoTributaria><infoFactura><fechaEmision>25/05/2023</fechaEmision><dirEstablecimiento>10 DE AGOSTO S/N Y FRANCISCO MOSCOSO</dirEstablecimiento><obligadoContabilidad>NO</obligadoContabilidad><tipoIdentificacionComprador>05</tipoIdentificacionComprador><razonSocialComprador>MACHUCA RUBIO JONNATHAN BRAULIO</razonSocialComprador><identificacionComprador>0104966189</identificacionComprador><totalSinImpuestos>18</totalSinImpuestos><totalDescuento>0</totalDescuento><totalConImpuestos><totalImpuesto><codigo>2</codigo><codigoPorcentaje>0</codigoPorcentaje><baseImponible>18</baseImponible><valor>0.00</valor></totalImpuesto></totalConImpuestos><propina>0.00</propina><importeTotal>18</importeTotal><moneda>DOLAR</moneda><pagos><pago><formaPago>01</formaPago><total>18</total></pago></pagos></infoFactura><detalles><detalle><codigoPrincipal>01</codigoPrincipal><codigoAuxiliar>01</codigoAuxiliar><descripcion>ALIMENTACION</descripcion><cantidad>1</cantidad><precioUnitario>18</precioUnitario><descuento>0</descuento><precioTotalSinImpuesto>18</precioTotalSinImpuesto><impuestos><impuesto><codigo>2</codigo><codigoPorcentaje>0</codigoPorcentaje><tarifa>0</tarifa><baseImponible>18</baseImponible><valor>0</valor></impuesto></impuestos></detalle></detalles><infoAdicional><campoAdicional nombre='Direccion'>AV 27 DE FEBRERO Y JAIME ROSALES</campoAdicional><campoAdicional nombre='Telefono'>2889441</campoAdicional><campoAdicional nombre='Email'>brauliomachuca@outlook.com</campoAdicional><campoAdicional nombre='Observaciones'> CONTRIBUYENTE REGIMEN RIMPE             </campoAdicional></infoAdicional></factura>